setup.py
txmetrics/__init__.py
txmetrics/pds_redis.py
txmetrics.egg-info/PKG-INFO
txmetrics.egg-info/SOURCES.txt
txmetrics.egg-info/dependency_links.txt
txmetrics.egg-info/requires.txt
txmetrics.egg-info/top_level.txt