Metadata-Version: 1.0
Name: txmetrics
Version: 0.2
Summary: simple python metrics for twisted
Home-page: https://github.com/gleicon/txmetrics
Author: Gleicon Moraes
Author-email: gleicon@gmail.com
License: UNKNOWN
Keywords: twisted metrics redis
Platform: UNKNOWN
